README.md
setup.py
pyine/__init__.py
pyine/convert.py
pyine.egg-info/PKG-INFO
pyine.egg-info/SOURCES.txt
pyine.egg-info/dependency_links.txt
pyine.egg-info/top_level.txt