Metadata-Version: 2.1
Name: pyine
Version: 1.1.2
Summary: A package that can be used to convert from pine script to python
Home-page: UNKNOWN
Author: Tom Callan
Author-email: tomcallan0@outlook.com
License: UNKNOWN
Platform: UNKNOWN
Classifier: Programming Language :: Python :: 3
Classifier: License :: OSI Approved :: MIT License
Classifier: Operating System :: OS Independent
